pt_utils/__init__.py
pt_utils-0.0.1.dist-info/LICENSE
pt_utils-0.0.1.dist-info/METADATA
pt_utils-0.0.1.dist-info/WHEEL
pt_utils-0.0.1.dist-info/top_level.txt
pt_utils-0.0.1.dist-info/RECORD
